ask_for_color/__init__.py
ask_for_color/ask_for_color.py
ask_for_color-0.1.3.dist-info/METADATA
ask_for_color-0.1.3.dist-info/WHEEL
ask_for_color-0.1.3.dist-info/top_level.txt
ask_for_color-0.1.3.dist-info/RECORD
